R2taps/__init__.py
R2taps-1.1.dist-info/METADATA
R2taps-1.1.dist-info/WHEEL
R2taps-1.1.dist-info/top_level.txt
R2taps-1.1.dist-info/RECORD
