Metadata-Version: 2.1
Name: R2taps
Version: 1.1
Summary: xdxdxdxdx
Author: SUHOFRUKT
Author-email: di.momopog@yandex.ru
Classifier: Programming Language :: Python :: 3
Classifier: License :: OSI Approved :: MIT License
Classifier: Operating System :: OS Independent
Requires-Python: >=3.6
